{"nodes": [{"id": "backend_app_core_allergy_catalog_py", "label": "allergy_catalog.py", "file_type": "code", "source_file": "backend\\app\\core\\allergy_catalog.py", "source_location": "L1"}, {"id": "allergy_catalog_normalize_term", "label": "_normalize_term()", "file_type": "code", "source_file": "backend\\app\\core\\allergy_catalog.py", "source_location": "L307"}, {"id": "allergy_catalog_basic_variants", "label": "_basic_variants()", "file_type": "code", "source_file": "backend\\app\\core\\allergy_catalog.py", "source_location": "L311"}, {"id": "allergy_catalog_get_default_allergies", "label": "get_default_allergies()", "file_type": "code", "source_file": "backend\\app\\core\\allergy_catalog.py", "source_location": "L330"}, {"id": "allergy_catalog_get_allergy_aliases", "label": "get_allergy_aliases()", "file_type": "code", "source_file": "backend\\app\\core\\allergy_catalog.py", "source_location": "L337"}, {"id": "allergy_catalog_expand_allergy_terms", "label": "expand_allergy_terms()", "file_type": "code", "source_file": "backend\\app\\core\\allergy_catalog.py", "source_location": "L358"}], "edges": [{"source": "backend_app_core_allergy_catalog_py", "target": "re", "relation": "imports", "confidence": "EXTRACTED", "source_file": "backend\\app\\core\\allergy_catalog.py", "source_location": "L3", "weight": 1.0}, {"source": "backend_app_core_allergy_catalog_py", "target": "typing", "relation": "imports_from", "confidence": "EXTRACTED", "source_file": "backend\\app\\core\\allergy_catalog.py", "source_location": "L4", "weight": 1.0}, {"source": "backend_app_core_allergy_catalog_py", "target": "allergy_catalog_normalize_term", "relation": "contains", "confidence": "EXTRACTED", "source_file": "backend\\app\\core\\allergy_catalog.py", "source_location": "L307", "weight": 1.0}, {"source": "backend_app_core_allergy_catalog_py", "target": "allergy_catalog_basic_variants", "relation": "contains", "confidence": "EXTRACTED", "source_file": "backend\\app\\core\\allergy_catalog.py", "source_location": "L311", "weight": 1.0}, {"source": "backend_app_core_allergy_catalog_py", "target": "allergy_catalog_get_default_allergies", "relation": "contains", "confidence": "EXTRACTED", "source_file": "backend\\app\\core\\allergy_catalog.py", "source_location": "L330", "weight": 1.0}, {"source": "backend_app_core_allergy_catalog_py", "target": "allergy_catalog_get_allergy_aliases", "relation": "contains", "confidence": "EXTRACTED", "source_file": "backend\\app\\core\\allergy_catalog.py", "source_location": "L337", "weight": 1.0}, {"source": "backend_app_core_allergy_catalog_py", "target": "allergy_catalog_expand_allergy_terms", "relation": "contains", "confidence": "EXTRACTED", "source_file": "backend\\app\\core\\allergy_catalog.py", "source_location": "L358", "weight": 1.0}, {"source": "allergy_catalog_basic_variants", "target": "allergy_catalog_normalize_term", "relation": "calls", "confidence": "EXTRACTED", "source_file": "backend\\app\\core\\allergy_catalog.py", "source_location": "L312", "weight": 1.0}, {"source": "allergy_catalog_get_allergy_aliases", "target": "allergy_catalog_normalize_term", "relation": "calls", "confidence": "EXTRACTED", "source_file": "backend\\app\\core\\allergy_catalog.py", "source_location": "L338", "weight": 1.0}, {"source": "allergy_catalog_get_allergy_aliases", "target": "allergy_catalog_basic_variants", "relation": "calls", "confidence": "EXTRACTED", "source_file": "backend\\app\\core\\allergy_catalog.py", "source_location": "L350", "weight": 1.0}, {"source": "allergy_catalog_expand_allergy_terms", "target": "allergy_catalog_normalize_term", "relation": "calls", "confidence": "EXTRACTED", "source_file": "backend\\app\\core\\allergy_catalog.py", "source_location": "L365", "weight": 1.0}, {"source": "allergy_catalog_expand_allergy_terms", "target": "allergy_catalog_basic_variants", "relation": "calls", "confidence": "EXTRACTED", "source_file": "backend\\app\\core\\allergy_catalog.py", "source_location": "L368", "weight": 1.0}, {"source": "allergy_catalog_expand_allergy_terms", "target": "allergy_catalog_get_allergy_aliases", "relation": "calls", "confidence": "EXTRACTED", "source_file": "backend\\app\\core\\allergy_catalog.py", "source_location": "L370", "weight": 1.0}], "raw_calls": [{"caller_nid": "allergy_catalog_normalize_term", "callee": "sub", "source_file": "backend\\app\\core\\allergy_catalog.py", "source_location": "L308"}, {"caller_nid": "allergy_catalog_normalize_term", "callee": "lower", "source_file": "backend\\app\\core\\allergy_catalog.py", "source_location": "L308"}, {"caller_nid": "allergy_catalog_normalize_term", "callee": "strip", "source_file": "backend\\app\\core\\allergy_catalog.py", "source_location": "L308"}, {"caller_nid": "allergy_catalog_basic_variants", "callee": "set", "source_file": "backend\\app\\core\\allergy_catalog.py", "source_location": "L314"}, {"caller_nid": "allergy_catalog_basic_variants", "callee": "endswith", "source_file": "backend\\app\\core\\allergy_catalog.py", "source_location": "L317"}, {"caller_nid": "allergy_catalog_basic_variants", "callee": "len", "source_file": "backend\\app\\core\\allergy_catalog.py", "source_location": "L317"}, {"caller_nid": "allergy_catalog_basic_variants", "callee": "add", "source_file": "backend\\app\\core\\allergy_catalog.py", "source_location": "L318"}, {"caller_nid": "allergy_catalog_basic_variants", "callee": "endswith", "source_file": "backend\\app\\core\\allergy_catalog.py", "source_location": "L319"}, {"caller_nid": "allergy_catalog_basic_variants", "callee": "len", "source_file": "backend\\app\\core\\allergy_catalog.py", "source_location": "L319"}, {"caller_nid": "allergy_catalog_basic_variants", "callee": "add", "source_file": "backend\\app\\core\\allergy_catalog.py", "source_location": "L320"}, {"caller_nid": "allergy_catalog_basic_variants", "callee": "endswith", "source_file": "backend\\app\\core\\allergy_catalog.py", "source_location": "L321"}, {"caller_nid": "allergy_catalog_basic_variants", "callee": "len", "source_file": "backend\\app\\core\\allergy_catalog.py", "source_location": "L321"}, {"caller_nid": "allergy_catalog_basic_variants", "callee": "add", "source_file": "backend\\app\\core\\allergy_catalog.py", "source_location": "L322"}, {"caller_nid": "allergy_catalog_basic_variants", "callee": "endswith", "source_file": "backend\\app\\core\\allergy_catalog.py", "source_location": "L323"}, {"caller_nid": "allergy_catalog_basic_variants", "callee": "len", "source_file": "backend\\app\\core\\allergy_catalog.py", "source_location": "L323"}, {"caller_nid": "allergy_catalog_basic_variants", "callee": "add", "source_file": "backend\\app\\core\\allergy_catalog.py", "source_location": "L324"}, {"caller_nid": "allergy_catalog_basic_variants", "callee": "endswith", "source_file": "backend\\app\\core\\allergy_catalog.py", "source_location": "L325"}, {"caller_nid": "allergy_catalog_basic_variants", "callee": "add", "source_file": "backend\\app\\core\\allergy_catalog.py", "source_location": "L326"}, {"caller_nid": "allergy_catalog_get_default_allergies", "callee": "str", "source_file": "backend\\app\\core\\allergy_catalog.py", "source_location": "L332"}, {"caller_nid": "allergy_catalog_get_default_allergies", "callee": "get", "source_file": "backend\\app\\core\\allergy_catalog.py", "source_location": "L332"}, {"caller_nid": "allergy_catalog_get_default_allergies", "callee": "items", "source_file": "backend\\app\\core\\allergy_catalog.py", "source_location": "L333"}, {"caller_nid": "allergy_catalog_get_allergy_aliases", "callee": "get", "source_file": "backend\\app\\core\\allergy_catalog.py", "source_location": "L343"}, {"caller_nid": "allergy_catalog_get_allergy_aliases", "callee": "extend", "source_file": "backend\\app\\core\\allergy_catalog.py", "source_location": "L345"}, {"caller_nid": "allergy_catalog_get_allergy_aliases", "callee": "str", "source_file": "backend\\app\\core\\allergy_catalog.py", "source_location": "L345"}, {"caller_nid": "allergy_catalog_get_allergy_aliases", "callee": "get", "source_file": "backend\\app\\core\\allergy_catalog.py", "source_location": "L345"}, {"caller_nid": "allergy_catalog_get_allergy_aliases", "callee": "set", "source_file": "backend\\app\\core\\allergy_catalog.py", "source_location": "L347"}, {"caller_nid": "allergy_catalog_get_allergy_aliases", "callee": "sorted", "source_file": "backend\\app\\core\\allergy_catalog.py", "source_location": "L350"}, {"caller_nid": "allergy_catalog_get_allergy_aliases", "callee": "add", "source_file": "backend\\app\\core\\allergy_catalog.py", "source_location": "L353"}, {"caller_nid": "allergy_catalog_get_allergy_aliases", "callee": "append", "source_file": "backend\\app\\core\\allergy_catalog.py", "source_location": "L354"}, {"caller_nid": "allergy_catalog_expand_allergy_terms", "callee": "set", "source_file": "backend\\app\\core\\allergy_catalog.py", "source_location": "L363"}, {"caller_nid": "allergy_catalog_expand_allergy_terms", "callee": "update", "source_file": "backend\\app\\core\\allergy_catalog.py", "source_location": "L368"}, {"caller_nid": "allergy_catalog_expand_allergy_terms", "callee": "update", "source_file": "backend\\app\\core\\allergy_catalog.py", "source_location": "L370"}]}